{
  "generated_at": "2026-06-12T05:15:14.226220+08:00",
  "total_titles_processed": 427,
  "failed_sources": [],
  "trends": [
    {
      "keyword_group": "游戏 用户体验 交互设计",
      "match_count": 1,
      "titles": [
        {
          "title": "电子游戏史上有哪些全世界玩家一起共创的传奇事件？",
          "url": "https://www.zhihu.com/question/2043732532701681460",
          "source": "知乎",
          "ranks": [
            11,
            15
          ],
          "is_new": false,
          "appearance_count": 3,
          "time_info": "[02时08分 ~ 05时15分]"
        }
      ]
    }
  ],
  "report_image_url": "https://joyce677.github.io/TrendRadar/img/news.jpg"
}