{
  "generated_at": "2026-05-28T07:56:44.252555+08:00",
  "total_titles_processed": 549,
  "failed_sources": [],
  "trends": [
    {
      "keyword_group": "游戏 用户体验 交互设计",
      "match_count": 1,
      "titles": [
        {
          "title": "女子网吧打游戏开挂被发现与老板争执",
          "url": "https://www.toutiao.com/trending/7644304986037289014/",
          "source": "今日头条",
          "ranks": [
            22,
            18,
            24
          ],
          "is_new": false,
          "appearance_count": 5,
          "time_info": "[01时54分 ~ 06时27分]"
        }
      ]
    }
  ],
  "report_image_url": "https://joyce677.github.io/TrendRadar/img/news.jpg"
}